__init__.py
ubkg_api/__init__.py
ubkg_api/app.py
ubkg_api/neo4j_connection_helper.py
ubkg_api/wsgi.py
ubkg_api/common_routes/__init__.py
ubkg_api/common_routes/common_neo4j_logic.py
ubkg_api/common_routes/codes/__init__.py
ubkg_api/common_routes/codes/codes_controller.py
ubkg_api/common_routes/concepts/__init__.py
ubkg_api/common_routes/concepts/concepts_controller.py
ubkg_api/common_routes/database/__init__.py
ubkg_api/common_routes/database/database_controller.py
ubkg_api/common_routes/deprecated/__init__.py
ubkg_api/common_routes/deprecated/validate.py
ubkg_api/common_routes/deprecated/tui/__init__.py
ubkg_api/common_routes/deprecated/tui/tui_controller.py
ubkg_api/common_routes/node_types/__init__.py
ubkg_api/common_routes/node_types/node_types_controller.py
ubkg_api/common_routes/property_types/__init__.py
ubkg_api/common_routes/property_types/property_types_controller.py
ubkg_api/common_routes/relationship_types/__init__.py
ubkg_api/common_routes/relationship_types/relationship_types_controller.py
ubkg_api/common_routes/sabs/__init__.py
ubkg_api/common_routes/sabs/sabs_controller.py
ubkg_api/common_routes/semantics/__init__.py
ubkg_api/common_routes/semantics/semantics_controller.py
ubkg_api/common_routes/sources/__init__.py
ubkg_api/common_routes/sources/sources_controller.py
ubkg_api/common_routes/status/__init__.py
ubkg_api/common_routes/status/status_controller.py
ubkg_api/common_routes/terms/__init__.py
ubkg_api/common_routes/terms/terms_controller.py
ubkg_api/cypher/code_code_id_terms.cypher
ubkg_api/cypher/codes_code_id_codes.cypher
ubkg_api/cypher/codes_code_id_concepts.cypher
ubkg_api/cypher/concepts_expand.cypher
ubkg_api/cypher/concepts_nodes.cypher
ubkg_api/cypher/concepts_shortestpath.cypher
ubkg_api/cypher/concepts_spanning_tree.cypher
ubkg_api/cypher/concepts_subgraph.cypher
ubkg_api/cypher/concepts_subgraph_sequential.cypher
ubkg_api/cypher/node_types.cypher
ubkg_api/cypher/node_types_by_sab.cypher
ubkg_api/cypher/sabs_codes_counts.cypher
ubkg_api-2.2.3.dist-info/licenses/LICENSE
ubkg_api-2.2.3.dist-info/METADATA
ubkg_api-2.2.3.dist-info/WHEEL
ubkg_api-2.2.3.dist-info/top_level.txt
ubkg_api-2.2.3.dist-info/RECORD
