Metadata-Version: 2.4
Name: ubkg_api
Version: 2.2.3
Summary: A REST API in front of the Unified Biomedical Knowlegde Graph
Author-email: HuBMAP Consortium <api-developers@hubmapconsortium.org>
Project-URL: Homepage, https://github.com/x-atlas-consortia/ubkg-api
Project-URL: Bug Tracker, https://github.com/x-atlas-consortia/ubkg-api/issues
Classifier: Programming Language :: Python :: 3
Classifier: License :: OSI Approved :: MIT License
Classifier: Operating System :: OS Independent
Requires-Python: >=3.9
License-File: LICENSE
Requires-Dist: python_dateutil>=2.6.0
Requires-Dist: setuptools>=21.0.0
Requires-Dist: Flask==3.0.3
Requires-Dist: neo4j==5.15.0
Dynamic: license-file
